{"data": [{"type": "hot_list_feed", "style_type": "1", "id": "0_1618200697.2105622", "card_id": "Q_454054826", "feed_specific": {"answer_count": 604}, "target": {"title_area": {"text": "如何看待美国黑人军官被两名白人警察拦下殴打、喷辣椒水？"}, "excerpt_area": {"text": "据美国广播公司（ABC）10 日报道，4 月 2 日提交的诉讼显示，2020 年 12 月，两名警察乔·古铁雷斯（Joe Gutierrez）和丹尼尔·克罗克（Daniel Crocker）将从执勤地点驱车回家的美国陆军少尉卡隆·纳扎里奥（Caron Nazario）拦下，称纳扎里奥驾驶无照车且「逃避执法」。纳扎里奥是一名拉丁裔陆军少尉，他当时穿着军官制服，驾驶着一辆刚买来的新车，未上永久车牌，但后窗上有临时车牌。纳扎里奥在诉讼中表示，他的宪法权利受到侵犯，要求进行相应的赔偿和惩罚性赔偿。黑人军官被美国警察揍哭，心碎质问"}, "image_area": {"url": "https://pic4.zhimg.com/80/v2-213aa93660c086c9fd1b72b27726998c_720w.jpg?source=1940ef5c"}, "metrics_area": {"text": "3809 万热度"}, "label_area": {"type": "trend", "trend": 0, "night_color": "#B7302D", "normal_color": "#F1403C"}, "link": {"url": "https://www.zhihu.com/question/454054826"}}, "attached_info": "Cj8IyOOBkpH0yqFSEAMaCDYzMTgwNzI1IIDKyoMGMFk45g1AAHIJNDU0MDU0ODI2eACqAQliaWxsYm9hcmTSAQA="}, {"type": "hot_list_feed", "style_type": "1", "id": "1_1618200697.211428", "card_id": "Q_453795080", "feed_specific": {"answer_count": 219}, "target": {"title_area": {"text": "日本政府基本决定将福岛核污水排入大海，真的没办法阻止了吗？"}, "excerpt_area": {"text": "真的不是网上说说，和简单谴责一下就可以的问题了。真的很恐怖的事情。 人类命运从此又多了诸多不测。去看看那些因为核辐射变异的人和动物，可怕地我都不敢贴图了，如果问题要等几十年或者上百年后出现，特别是海洋里食物链顶端的动物慢慢积累核辐射等物质，如果海洋变成了一个毒缸，那还怎么活。真要朝着科幻小说恐怖电影方向发展了。 别说日本，全世界都要搭进去了。难道这个时候就没有一个能动员起来的国际组织了吗？为什么人类对于潜在的危害这么麻木？！人民日报 - 有品质的新闻"}, "image_area": {"url": "https://pic4.zhimg.com/80/v2-f1afafe6d478f405da018a77ebe2c80a_720w.png"}, "metrics_area": {"text": "1078 万热度"}, "label_area": {"type": "trend", "trend": 0, "night_color": "#B7302D", "normal_color": "#F1403C"}, "link": {"url": "https://www.zhihu.com/question/453795080"}}, "attached_info": "Cj8IyOOBkpH0yqFSEAMaCDYzMTIyOTc5IOzewYMGMBc4ggZAAXIJNDUzNzk1MDgweACqAQliaWxsYm9hcmTSAQA="}, {"type": "hot_list_feed", "style_type": "1", "id": "2_1618200697.21201", "card_id": "Q_454063985", "feed_specific": {"answer_count": 821}, "target": {"title_area": {"text": "岳云鹏称 128G 手机可用内存仅 112G，系统内存应厂家消化，你认同吗？可用内存与宣传不符算虚假宣传吗？"}, "excerpt_area": {"text": ""}, "image_area": {"url": "https://pic1.zhimg.com/80/v2-a600ff16dd633c7ff5bf147f12624e3d_720w.png"}, "metrics_area": {"text": "1057 万热度"}, "label_area": {"type": "trend", "trend": 0, "night_color": "#B7302D", "normal_color": "#F1403C"}, "link": {"url": "https://www.zhihu.com/question/454063985"}}, "attached_info": "CkAIyOOBkpH0yqFSEAMaCDYzMTgyNzc2IIjlyoMGMIIBOL4SQAJyCTQ1NDA2Mzk4NXgAqgEJYmlsbGJvYXJk0gEA"}, {"type": "hot_list_feed", "style_type": "1", "id": "3_1618200697.2124846", "card_id": "Q_441692710", "feed_specific": {"answer_count": 629}, "target": {"title_area": {"text": "未来 5 年，有没有取代房子的最好投资？"}, "excerpt_area": {"text": ""}, "image_area": {"url": "https://pic1.zhimg.com/80/v2-40289c16f9c4a4184dc8751d35bc4721_720w.jpg?source=1940ef5c"}, "metrics_area": {"text": "874 万热度"}, "label_area": {"type": "trend", "trend": 0, "night_color": "#B7302D", "normal_color": "#F1403C"}, "link": {"url": "https://www.zhihu.com/question/441692710"}}, "attached_info": "Cj8IyOOBkpH0yqFSEAMaCDYwNDMxODMyILyXyoAGMCs4pkFAA3IJNDQxNjkyNzEweACqAQliaWxsYm9hcmTSAQA="}, {"type": "hot_list_feed", "style_type": "1", "id": "4_1618200697.2128882", "card_id": "Q_454174504", "feed_specific": {"answer_count": 79}, "target": {"title_area": {"text": "如何看待阿里巴巴张勇回应称，监管部门的反垄断处罚不会造成重大影响？"}, "excerpt_area": {"text": "4 月 12 日上午 8 点，阿里巴巴召开电话会议，讨论行政处罚决定。4 月 10 日，市场监管总局依法对阿里巴巴集团作出行政处罚，并处以其 2019 年销售额 4% 计 182.28 亿元罚款。 阿里巴巴董事局主席兼 CEO 张勇表示，预计监管部门的反垄断处罚不会造成重大影响；将会作出更多行动减少商户经营成本；更多业已成熟的业务将会转为免费；公司已准备了数十亿元资金支持新项目。阿里巴巴 CEO 张勇：预计监管部门的反垄断处罚不会造成重大影响"}, "image_area": {"url": "https://pic4.zhimg.com/80/v2-553ac755fc10aad34ada1416bb8293ff_720w.png"}, "metrics_area": {"text": "625 万热度"}, "label_area": {"type": "trend", "trend": 0, "night_color": "#B7302D", "normal_color": "#F1403C"}, "link": {"url": "https://www.zhihu.com/question/454174504"}}, "attached_info": "Cj8IyOOBkpH0yqFSEAMaCDYzMjA3MzAzIN3IzoMGMAo4ngNABHIJNDU0MTc0NTA0eACqAQliaWxsYm9hcmTSAQA="}, {"type": "hot_list_feed", "style_type": "1", "id": "5_1618200697.2134454", "card_id": "Q_454094663", "feed_specific": {"answer_count": 114}, "target": {"title_area": {"text": "贤合庄火锅店天花板掉落，致夫妻俩一个手骨折一个脸被烫，火锅店应承担怎样的责任？"}, "excerpt_area": {"text": "最新进展：陈赫火锅店道歉声明 有网友称在陈赫火锅店就餐时被掉落的天花板砸伤，还有人被烫伤，刚刚，火锅店官博发布致歉声明，称已在第一时间与受伤顾客协调解决并进行赔偿，现双方达成和解。随后，@陈赫 也转发道歉，「再次向两位顾客深表歉意，全面排查整改，安全问题绝不姑息！」 ​ 李女士和丈夫去贤合庄卤味火锅杭州万达店用餐，辣锅上来刚要开吃，天花板砸下来。夫妻俩一个手骨折一个脸被烫，都很受伤。 火锅店声明："}, "image_area": {"url": "https://pic1.zhimg.com/80/v2-7191aa38faad954708f0bb8a440f7b39_720w.png"}, "metrics_area": {"text": "551 万热度"}, "label_area": {"type": "trend", "trend": 0, "night_color": "#B7302D", "normal_color": "#F1403C"}, "link": {"url": "https://www.zhihu.com/question/454094663"}}, "attached_info": "Cj8IyOOBkpH0yqFSEAMaCDYzMTg5NTcxIK3Dy4MGMA44tAdABXIJNDU0MDk0NjYzeACqAQliaWxsYm9hcmTSAQA="}, {"type": "hot_list_feed", "style_type": "1", "id": "6_1618200697.213988", "card_id": "Q_453979353", "feed_specific": {"answer_count": 131}, "target": {"title_area": {"text": "为什么《进击的巨人》在结局借鉴了叛逆鲁鲁修的结局却不如鲁鲁修获得广大好评？"}, "excerpt_area": {"text": ""}, "image_area": {"url": "https://pic2.zhimg.com/80/v2-8143d545aa6d30c437c06af2d262602c_720w.jpg?source=1940ef5c"}, "metrics_area": {"text": "500 万热度"}, "label_area": {"type": "trend", "trend": 0, "night_color": "#B7302D", "normal_color": "#F1403C"}, "link": {"url": "https://www.zhihu.com/question/453979353"}}, "attached_info": "Cj8IyOOBkpH0yqFSEAMaCDYzMTYzODI2IO+/x4MGMBk49QNABnIJNDUzOTc5MzUzeACqAQliaWxsYm9hcmTSAQA="}, {"type": "hot_list_feed", "style_type": "1", "id": "7_1618200697.2143764", "card_id": "Q_453752819", "feed_specific": {"answer_count": 59}, "target": {"title_area": {"text": "如何看待 50 吨卡车侧翻，被压沃尔沃车主一家毫发无伤？"}, "excerpt_area": {"text": "从下面这个视频可以看到，不久前，一辆沃尔沃车辆被翻覆的货车整个压住，卡车整体约重 50 吨。在经过 2 个小时的救援后，车主一家被消防员全部救出，均毫发无伤。可以看到沃尔沃车身撑住了整个卡车的重量，引发了许多专业人士和网友的关注，对此你怎么看？（信息来源：事件发生于 2020 年 6 月 29 日江西省上万高速公路，此视频由沃尔沃生命奇迹俱乐部拍摄记录）沃尔沃生命奇迹俱乐部"}, "image_area": {"url": "https://pic2.zhimg.com/80/v2-d50b2df5ee45aa40abb4b7dc838e0172_720w.jpg?source=1940ef5c"}, "metrics_area": {"text": "424 万热度"}, "label_area": {"type": "trend", "trend": 0, "night_color": "#B7302D", "normal_color": "#F1403C"}, "link": {"url": "https://www.zhihu.com/question/453752819"}}, "attached_info": "Cj8IyOOBkpH0yqFSEAMaCDYzMTEzNjE2IJnfwIMGMAA4wANAB3IJNDUzNzUyODE5eACqAQliaWxsYm9hcmTSAQA="}, {"type": "hot_list_feed", "style_type": "1", "id": "8_1618200697.2149184", "card_id": "Q_454041221", "feed_specific": {"answer_count": 151}, "target": {"title_area": {"text": "如何看待德国研究机构称，日本核污水 57 天将污染半个太平洋？这将对海洋生态以及周边国家产生什么影响？"}, "excerpt_area": {"text": "【研究显示：从排放之日起 日本核污水 57 天将污染半个太平洋】日本核污水排入大海影响有多大？含有放射性物质的污水一旦被排入大海会造成什么影响？ 首先，日本太平洋沿岸海域将受到影响，特别是福岛县周边局部水域，之后污水还会污染东海。一家来自德国的海洋科学研究机构的计算结果显示，从排放之日起，57 天内放射性物质就将扩散至太平洋大半区域，3 年后美国和加拿大就将遭到核污染影响。（央视网）"}, "image_area": {"url": "https://pic2.zhimg.com/80/v2-066eaf2b71c7296c33927fa529015cf1_720w.png"}, "metrics_area": {"text": "418 万热度"}, "label_area": {"type": "trend", "trend": 0, "night_color": "#B7302D", "normal_color": "#F1403C"}, "link": {"url": "https://www.zhihu.com/question/454041221"}}, "attached_info": "ClUIyOOBkpH0yqFSEAMaCDYzMTc3NjQ4IN2fyoMGMA845wZACHIJNDU0MDQxMjIxeACqAQliaWxsYm9hcmTSAQDyARMIARIPZG9tYWluX29wZXJhdG9y"}, {"type": "hot_list_feed", "style_type": "1", "id": "9_1618200697.2154467", "card_id": "EV_12216978", "feed_specific": {"answer_count": 0}, "target": {"title_area": {"text": "历史上有哪些突显外交智慧的经典例子？"}, "excerpt_area": {"text": ""}, "image_area": {"url": "https://pic3.zhimg.com/v2-896e8670ec6faded2992186487d2415c.png"}, "metrics_area": {"text": "历史环游记·外交风云"}, "label_area": {"type": "trend", "trend": 0, "night_color": "#B7302D", "normal_color": "#F1403C"}, "link": {"url": "https://www.zhihu.com/xen/market/ecom-page/1363902650296258560"}}, "attached_info": "Cn0IyOOBkpH0yqFSEBgaBDYwNjIgrr3AgwZACXIIMTIyMTY5Nzh4AKoBCWJpbGxib2FyZMoBPmh0dHBzOi8vd3d3LnpoaWh1LmNvbS94ZW4vbWFya2V0L2Vjb20tcGFnZS8xMzYzOTAyNjUwMjk2MjU4NTYw8gEHCAESA3ZpcA=="}, {"type": "hot_list_feed", "style_type": "1", "id": "10_1618200697.215714", "card_id": "Q_453877246", "feed_specific": {"answer_count": 195}, "target": {"title_area": {"text": "王小波逝世 24 周年之际，你有什么对小波说的吗？"}, "excerpt_area": {"text": ""}, "image_area": {"url": "https://pic4.zhimg.com/80/v2-39399b730beebace6269d115dd07d421_720w.jpg?source=1940ef5c"}, "metrics_area": {"text": "413 万热度"}, "label_area": {"type": "trend", "trend": 0, "night_color": "#B7302D", "normal_color": "#F1403C"}, "link": {"url": "https://www.zhihu.com/question/453877246"}}, "attached_info": "ClUIyOOBkpH0yqFSEAMaCDYzMTQxMjM1IIqVxYMGMA44iwdACnIJNDUzODc3MjQ2eACqAQliaWxsYm9hcmTSAQDyARMIARIPZG9tYWluX29wZXJhdG9y"}, {"type": "hot_list_feed", "style_type": "1", "id": "11_1618200697.2161648", "card_id": "Q_454001392", "feed_specific": {"answer_count": 154}, "target": {"title_area": {"text": "如何评价许嵩新歌《昨夜书》？"}, "excerpt_area": {"text": "《经典咏流传》中，许嵩献唱新作《昨夜书》，大家觉得怎么样？"}, "image_area": {"url": "https://pic1.zhimg.com/80/v2-00d29a1d5a31e225255bd397ba1f8531_720w.png"}, "metrics_area": {"text": "411 万热度"}, "label_area": {"type": "trend", "trend": 0, "night_color": "#B7302D", "normal_color": "#F1403C"}, "link": {"url": "https://www.zhihu.com/question/454001392"}}, "attached_info": "Cj8IyOOBkpH0yqFSEAMaCDYzMTY4Njg4IKahyYMGMAQ4mgRAC3IJNDU0MDAxMzkyeACqAQliaWxsYm9hcmTSAQA="}, {"type": "hot_list_feed", "style_type": "1", "id": "12_1618200697.216629", "card_id": "Q_454031777", "feed_specific": {"answer_count": 432}, "target": {"title_area": {"text": "如何看待游客在三亚吃海胆蒸蛋没海胆，官方称「当季本地海胆汁多肉少，未发现掉包」？如何从法律角度解读？"}, "excerpt_area": {"text": "近日，游客三亚吃海胆蒸蛋没海胆一事引发关注，11 日，三亚发布通报：经工作组调查，该饭店所销售海鲜品明码标价，未发现有海鲜掉包、掺杂掺假等价格欺诈行为。 据了解，当季本地海胆汁多肉少，与其他地区口味有所差异，一般采用蒸蛋的方式供客人食用。为证明当季海胆情况，纠纷发生时，涉事商家现场宰杀了一只海胆供消费者查实。民警介入协调后，商店免除了消费者消费海胆的费用，消费者实际支付 2427.6 元。 针对消费者微博中所称饭店女服务员语言威胁，经警方核查，并非涉事商家人员所说，可能是消费者上厕所时一名路过的女性对其所说，目前警方正寻找该女性进一步核实。 民警现场协调结束后，在返回警务室途中遇见消费者，见当时无来往车辆而帮助其返程，不存在消费者受威胁后由民警护送其返店的情况。 相关问题 1 月初在三亚的海鲜市场买了几个活的海胆，结果打开一看西米都木有 老板说海南海胆就这样，求解！？"}, "image_area": {"url": "https://pic4.zhimg.com/80/v2-f1ccff3c709365f90c644cd1d80f274c_720w.jpg?source=1940ef5c"}, "metrics_area": {"text": "392 万热度"}, "label_area": {"type": "trend", "trend": 0, "night_color": "#B7302D", "normal_color": "#F1403C"}, "link": {"url": "https://www.zhihu.com/question/454031777"}}, "attached_info": "Cj8IyOOBkpH0yqFSEAMaCDYzMTc1NTE3IPGCyoMGMCM4jAxADHIJNDU0MDMxNzc3eACqAQliaWxsYm9hcmTSAQA="}, {"type": "hot_list_feed", "style_type": "1", "id": "13_1618200697.2172859", "card_id": "Q_454071132", "feed_specific": {"answer_count": 389}, "target": {"title_area": {"text": "2021 LPL 春季胜者组决赛 FPX 3:2 击败 EDG 晋级总决赛，如何评价这场比赛？"}, "excerpt_area": {"text": "如何评价 FPX 战队在假赛风波，场外舆论，队员频换的情况下从季后赛八强直冲总决赛？为什么 2021 LPL 春季季后赛上蓝色方胜率这么高？2021 LPL 春季赛败者组决赛 EDG vs RNG 你更看好谁？"}, "image_area": {"url": "https://pic1.zhimg.com/80/v2-1134ee030d3b88c4945fac7fecedb164_720w.jpg?source=1940ef5c"}, "metrics_area": {"text": "375 万热度"}, "label_area": {"type": "trend", "trend": 0, "night_color": "#B7302D", "normal_color": "#F1403C"}, "link": {"url": "https://www.zhihu.com/question/454071132"}}, "attached_info": "Cj8IyOOBkpH0yqFSEAMaCDYzMTg0MzU0IOD5yoMGMBU4vwtADXIJNDU0MDcxMTMyeACqAQliaWxsYm9hcmTSAQA="}, {"type": "hot_list_feed", "style_type": "1", "id": "14_1618200697.2177947", "card_id": "Q_453811297", "feed_specific": {"answer_count": 175}, "target": {"title_area": {"text": "还有一个星期要在学校 LoL 比赛上解说了，可我不经常玩 LoL，如何恶补 LoL 知识呢？"}, "excerpt_area": {"text": ""}, "image_area": {"url": "https://pic2.zhimg.com/80/v2-857f6129592666dca189a810394ad030_720w.png"}, "metrics_area": {"text": "329 万热度"}, "label_area": {"type": "trend", "trend": 0, "night_color": "#B7302D", "normal_color": "#F1403C"}, "link": {"url": "https://www.zhihu.com/question/453811297"}}, "attached_info": "Cj8IyOOBkpH0yqFSEAMaCDYzMTI2NTkzIIGawoMGMBk4/wFADnIJNDUzODExMjk3eACqAQliaWxsYm9hcmTSAQA="}, {"type": "hot_list_feed", "style_type": "1", "id": "15_1618200697.2181852", "card_id": "Q_453500291", "feed_specific": {"answer_count": 35}, "target": {"title_area": {"text": "为什么手机计算器上 50%+50%=0.75?"}, "excerpt_area": {"text": ""}, "image_area": {"url": "https://pic4.zhimg.com/80/v2-559ed0a10a9b0f784e6119035954ceb3_720w.png"}, "metrics_area": {"text": "259 万热度"}, "label_area": {"type": "trend", "trend": 0, "night_color": "#B7302D", "normal_color": "#F1403C"}, "link": {"url": "https://www.zhihu.com/question/453500291"}}, "attached_info": "Cj4IyOOBkpH0yqFSEAMaCDYzMDU3MzYxIJbSuYMGMAE4ekAPcgk0NTM1MDAyOTF4AKoBCWJpbGxib2FyZNIBAA=="}, {"type": "hot_list_feed", "style_type": "1", "id": "16_1618200697.2186463", "card_id": "Q_454042280", "feed_specific": {"answer_count": 38}, "target": {"title_area": {"text": "如何看待《原神》的新主线 「我们终将重逢」？"}, "excerpt_area": {"text": "如何看待《原神》的新主线 「我们终将重逢」？"}, "image_area": {"url": "https://pic1.zhimg.com/80/v2-14f592378b9fbf3ef8c79cf5b60da836_720w.jpg?source=1940ef5c"}, "metrics_area": {"text": "250 万热度"}, "label_area": {"type": "trend", "trend": 0, "night_color": "#B7302D", "normal_color": "#F1403C"}, "link": {"url": "https://www.zhihu.com/question/454042280"}}, "attached_info": "Cj4IyOOBkpH0yqFSEAMaCDYzMTc3ODg5IMqjyoMGMAQ4WEAQcgk0NTQwNDIyODB4AKoBCWJpbGxib2FyZNIBAA=="}, {"type": "hot_list_feed", "style_type": "1", "id": "17_1618200697.2190661", "card_id": "Q_452831269", "feed_specific": {"answer_count": 45}, "target": {"title_area": {"text": "南京景区咸水鸭 100 五只，每只 800g 贵吗? 当作旅行伴手礼合适吗？"}, "excerpt_area": {"text": "800g"}, "image_area": {"url": "https://pic4.zhimg.com/80/v2-58862d741d429daf0a29ad9ac3073428_720w.jpg?source=1940ef5c"}, "metrics_area": {"text": "237 万热度"}, "label_area": {"type": "trend", "trend": 0, "night_color": "#B7302D", "normal_color": "#F1403C"}, "link": {"url": "https://www.zhihu.com/question/452831269"}}, "attached_info": "Cj4IyOOBkpH0yqFSEAMaCDYyOTA4ODAyIK7epIMGMAI4ZkARcgk0NTI4MzEyNjl4AKoBCWJpbGxib2FyZNIBAA=="}, {"type": "hot_list_feed", "style_type": "1", "id": "18_1618200697.2197247", "card_id": "Q_342843416", "feed_specific": {"answer_count": 528}, "target": {"title_area": {"text": "汉献帝为何不一剑杀了曹操，夺回大权？"}, "excerpt_area": {"text": "其实匹夫一怒，血溅五步，为什么汉献帝不直接手刃曹贼，拿回权利"}, "image_area": {"url": "https://pic2.zhimg.com/80/v2-a5f20b10c27e7508d5218ca34cb839aa_720w.png"}, "metrics_area": {"text": "229 万热度"}, "label_area": {"type": "trend", "trend": 0, "night_color": "#B7302D", "normal_color": "#F1403C"}, "link": {"url": "https://www.zhihu.com/question/342843416"}}, "attached_info": "Cj8IyOOBkpH0yqFSEAMaCDM4NDY0NTQ5IP7yjusFMB04ywZAEnIJMzQyODQzNDE2eACqAQliaWxsYm9hcmTSAQA="}, {"type": "hot_list_feed", "style_type": "1", "id": "19_1618200697.220185", "card_id": "Q_396974171", "feed_specific": {"answer_count": 130}, "target": {"title_area": {"text": "什么样的女生（男生）一看就很难追？"}, "excerpt_area": {"text": ""}, "image_area": {"url": "https://pic2.zhimg.com/80/v2-445348ba0c999139c860584e7f623cb5_720w.jpg?source=1940ef5c"}, "metrics_area": {"text": "227 万热度"}, "label_area": {"type": "trend", "trend": 0, "night_color": "#B7302D", "normal_color": "#F1403C"}, "link": {"url": "https://www.zhihu.com/question/396974171"}}, "attached_info": "Cj8IyOOBkpH0yqFSEAMaCDUwNDk1OTkxIKWcqPYFMAU4xwRAE3IJMzk2OTc0MTcxeACqAQliaWxsYm9hcmTSAQA="}, {"type": "hot_list_feed", "style_type": "1", "id": "20_1618200697.2205825", "card_id": "Q_443271607", "feed_specific": {"answer_count": 85}, "target": {"title_area": {"text": "TES 是怎么越打越差的？"}, "excerpt_area": {"text": "从 jackeylove 加盟后迎来的一波爆发，然后越来越差，问题出在哪？"}, "image_area": {"url": "https://pic4.zhimg.com/50/v2-1dc8c7a893a43bb9492d376bc93c3db1_720w.jpg?source=ba7200d9"}, "metrics_area": {"text": "206 万热度"}, "label_area": {"type": "trend", "trend": 0, "night_color": "#B7302D", "normal_color": "#F1403C"}, "link": {"url": "https://www.zhihu.com/question/443271607"}}, "attached_info": "Cj8IyOOBkpH0yqFSEAMaCDYwNzgyOTIwIMHJ/YAGMAM4gAFAFHIJNDQzMjcxNjA3eACqAQliaWxsYm9hcmTSAQA="}, {"type": "hot_list_feed", "style_type": "1", "id": "21_1618200697.220985", "card_id": "Q_454184476", "feed_specific": {"answer_count": 57}, "target": {"title_area": {"text": "如何看待郭美美等人售有毒减肥药案侦破， 75 人被抓，涉案金额超 5000 万？将承担什么法律后果？"}, "excerpt_area": {"text": "3 月 18 日，上海警方发布通报，郭美美因制销违禁减肥类食品，被警方刑拘。2019 年 7 月，郭美美因开设赌场罪被判刑。在刑满释放后的一年多时间里，她利用自己「网红」的「名声」，在网络平台大肆售卖有毒有害减肥类保健食品。 2020 年 12 月，浦东公安分局经侦支队收到一条线索，有人在网上销售假减肥药。该制售窝点通过在网上发布广告进行宣传，吸引消费者购买「特效减肥类保健食品」。殊不知，该窝点售卖的产品中添加了「西布曲明」的违禁成分，会对身体会造成伤害。 浦东经侦支队民警经过前期数月的缜密侦查，在市局经侦总队的指导协助下，会同外高桥公安处及相关派出所，在多省多地统一开展收网行动，先后抓获涉嫌生产、销售有毒有害减肥类保健食品的嫌疑人曾某某、周某某、郭某某等 75 人，其中就包括郭美美。 浦东警方捣毁生产窝点 3 处、销售窝点 24 处，现场查获有毒有害减肥类保健食品 65000 余粒、生产原料约 34 公斤、生产设备 3 台以及外包装 20000 余件，涉案金额达 5000 万余元。现涉案嫌疑人因涉嫌生产、销售有毒有害食品罪被依法采取强制措施。"}, "image_area": {"url": "https://pic4.zhimg.com/50/v2-f6e27aa04ca893370c7c3692cede602b_b.jpg"}, "metrics_area": {"text": "206 万热度"}, "label_area": {"type": "trend", "trend": 0, "night_color": "#B7302D", "normal_color": "#F1403C"}, "link": {"url": "https://www.zhihu.com/question/454184476"}}, "attached_info": "Cj8IyOOBkpH0yqFSEAMaCDYzMjA5NTA1ILjjzoMGMAU47AFAFXIJNDU0MTg0NDc2eACqAQliaWxsYm9hcmTSAQA="}, {"type": "hot_list_feed", "style_type": "1", "id": "22_1618200697.221696", "card_id": "Q_446794813", "feed_specific": {"answer_count": 59}, "target": {"title_area": {"text": "苹果公司知道我在使用黑苹果（Hackintosh）吗？"}, "excerpt_area": {"text": "这里附上如何打出： macOS：按下 Option+Shift+K 就可以打出一个 LOGO iPhone&iPad：打「苹果」然后在「联想」里面找到"}, "image_area": {"url": "https://pic4.zhimg.com/80/v2-9629d58ca7966ce4f678a037c3c7916c_720w.png"}, "metrics_area": {"text": "200 万热度"}, "label_area": {"type": "trend", "trend": 0, "night_color": "#B7302D", "normal_color": "#F1403C"}, "link": {"url": "https://www.zhihu.com/question/446794813"}}, "attached_info": "Cj8IyOOBkpH0yqFSEAMaCDYxNTY2MTg0IPW064EGMBs4rQVAFnIJNDQ2Nzk0ODEzeACqAQliaWxsYm9hcmTSAQA="}, {"type": "hot_list_feed", "style_type": "1", "id": "23_1618200697.222128", "card_id": "Q_429392239", "feed_specific": {"answer_count": 1989}, "target": {"title_area": {"text": "结过婚的女生对未婚女生有什么忠告？"}, "excerpt_area": {"text": ""}, "image_area": {"url": "https://pic4.zhimg.com/80/v2-469bfc2245bf8d59d6c247bbe931d2d8_720w.png"}, "metrics_area": {"text": "200 万热度"}, "label_area": {"type": "trend", "trend": 0, "night_color": "#B7302D", "normal_color": "#F1403C"}, "link": {"url": "https://www.zhihu.com/question/429392239"}}, "attached_info": "CkAIyOOBkpH0yqFSEAMaCDU3Njk5NzQyIKjQn/0FMC442pgBQBdyCTQyOTM5MjIzOXgAqgEJYmlsbGJvYXJk0gEA"}, {"type": "hot_list_feed", "style_type": "1", "id": "24_1618200697.2225482", "card_id": "Q_451242934", "feed_specific": {"answer_count": 45}, "target": {"title_area": {"text": "为什么空姐大多数都很瘦呢？"}, "excerpt_area": {"text": "为什么在国内我们看见的空姐大多数都很瘦呢，但在国外就胖瘦都有呢。？"}, "image_area": {"url": "https://pic4.zhimg.com/v2-6656876cf5d2e758ba8a627821898298_1440w.jpg?source=172ae18b"}, "metrics_area": {"text": "200 万热度"}, "label_area": {"type": "trend", "trend": 0, "night_color": "#B7302D", "normal_color": "#F1403C"}, "link": {"url": "https://www.zhihu.com/question/451242934"}}, "attached_info": "Cj4IyOOBkpH0yqFSEAMaCDYyNTU1NTE4IK+Y8oIGMAQ4Z0AYcgk0NTEyNDI5MzR4AKoBCWJpbGxib2FyZNIBAA=="}, {"type": "hot_list_feed", "style_type": "1", "id": "25_1618200697.2229476", "card_id": "Q_439584381", "feed_specific": {"answer_count": 323}, "target": {"title_area": {"text": "我花两千块买一个耳机，算智商税吗？"}, "excerpt_area": {"text": ""}, "image_area": {"url": "https://pic1.zhimg.com/80/v2-81f2a3e1e32277eafdf06809374d1f36_720w.jpg?source=1940ef5c"}, "metrics_area": {"text": "193 万热度"}, "label_area": {"type": "trend", "trend": 0, "night_color": "#B7302D", "normal_color": "#F1403C"}, "link": {"url": "https://www.zhihu.com/question/439584381"}}, "attached_info": "Cj8IyOOBkpH0yqFSEAMaCDU5OTYzNDYxIPb+hoAGMAk4hgRAGXIJNDM5NTg0MzgxeACqAQliaWxsYm9hcmTSAQA="}, {"type": "hot_list_feed", "style_type": "1", "id": "26_1618200697.223367", "card_id": "Q_453900623", "feed_specific": {"answer_count": 32}, "target": {"title_area": {"text": "2021 LCK 春季总决赛 DK 3:0 Gen.G 夺得春季赛冠军，如何评价这场比赛？"}, "excerpt_area": {"text": "2021 LCK 春季赛的 DK 相较去年是更强了还是更弱了？你对 DK 今年季中冠军赛的前景有哪些看法？"}, "image_area": {"url": "https://pic4.zhimg.com/80/v2-db06705bf9655cfaad641cf630d549a1_720w.jpg?source=1940ef5c"}, "metrics_area": {"text": "165 万热度"}, "label_area": {"type": "trend", "trend": 0, "night_color": "#B7302D", "normal_color": "#F1403C"}, "link": {"url": "https://www.zhihu.com/question/453900623"}}, "attached_info": "Cj4IyOOBkpH0yqFSEAMaCDYzMTQ2Mzg2IKnaxYMGMAA4XEAacgk0NTM5MDA2MjN4AKoBCWJpbGxib2FyZNIBAA=="}, {"type": "hot_list_feed", "style_type": "1", "id": "27_1618200697.223825", "card_id": "Q_454003603", "feed_specific": {"answer_count": 65}, "target": {"title_area": {"text": "如何看待专家称中国人均月流量十年后或达 100GB ？或将产生哪些影响？"}, "excerpt_area": {"text": "4 月 10 日，清华大学国家金融研究院院长 、 IMF 原副总裁朱民在 2021 清华五道口首席经济学家论坛上表示，中国人现在人均月流量是 9GB，高于 OECD 国家的 50%；10 年以后，2030 年 (中国) 人均流量大概会达到 100GB/ 月。（中新视频）"}, "image_area": {"url": "https://pic2.zhimg.com/80/v2-af9852b4e009c61475530f92d2f39e5e_720w.png"}, "metrics_area": {"text": "164 万热度"}, "label_area": {"type": "trend", "trend": 0, "night_color": "#B7302D", "normal_color": "#F1403C"}, "link": {"url": "https://www.zhihu.com/question/454003603"}}, "attached_info": "Cj8IyOOBkpH0yqFSEAMaCDYzMTY5MTkxIP6qyYMGMAw4rAFAG3IJNDU0MDAzNjAzeACqAQliaWxsYm9hcmTSAQA="}, {"type": "hot_list_feed", "style_type": "1", "id": "28_1618200697.2243304", "card_id": "Q_453524620", "feed_specific": {"answer_count": 34}, "target": {"title_area": {"text": "《进击的巨人》漫画结尾了，现在怎么比较《进击的巨人》与《东京喰种》？"}, "excerpt_area": {"text": ""}, "image_area": {"url": "https://pic2.zhimg.com/80/v2-d32963b270821847d9cd82db45d2c47f_720w.png"}, "metrics_area": {"text": "162 万热度"}, "label_area": {"type": "trend", "trend": 0, "night_color": "#B7302D", "normal_color": "#F1403C"}, "link": {"url": "https://www.zhihu.com/question/453524620"}}, "attached_info": "Cj4IyOOBkpH0yqFSEAMaCDYzMDYyNzQyIKGXuoMGMAE4SEAccgk0NTM1MjQ2MjB4AKoBCWJpbGxib2FyZNIBAA=="}, {"type": "hot_list_feed", "style_type": "1", "id": "29_1618200697.2246814", "card_id": "Q_453067159", "feed_specific": {"answer_count": 57}, "target": {"title_area": {"text": "如何评价大张伟获得《吐槽大会》第五季冠军？"}, "excerpt_area": {"text": ""}, "image_area": {"url": "https://pic2.zhimg.com/80/v2-b8430a5feb4f0cd858b1e7586a43339b_720w.jpg?source=1940ef5c"}, "metrics_area": {"text": "158 万热度"}, "label_area": {"type": "trend", "trend": 0, "night_color": "#B7302D", "normal_color": "#F1403C"}, "link": {"url": "https://www.zhihu.com/question/453067159"}}, "attached_info": "Cj4IyOOBkpH0yqFSEAMaCDYyOTYxMjI4IMT4q4MGMAE4XkAdcgk0NTMwNjcxNTl4AKoBCWJpbGxib2FyZNIBAA=="}, {"type": "hot_list_feed", "style_type": "1", "id": "30_1618200697.22502", "card_id": "Q_453765457", "feed_specific": {"answer_count": 59}, "target": {"title_area": {"text": "《山河令》大结局快半个月了，为什么我不仅没走出来还越陷越深？"}, "excerpt_area": {"text": "为什么我越来越心疼阿絮，现在都要心疼张哲瀚了。"}, "image_area": {"url": "https://pic4.zhimg.com/80/v2-63e20dd75f896aa247031bb9847518e0_720w.jpg?source=1940ef5c"}, "metrics_area": {"text": "140 万热度"}, "label_area": {"type": "trend", "trend": 0, "night_color": "#B7302D", "normal_color": "#F1403C"}, "link": {"url": "https://www.zhihu.com/question/453765457"}}, "attached_info": "Cj4IyOOBkpH0yqFSEAMaCDYzMTE2NDM0IIeKwYMGMAI4YEAecgk0NTM3NjU0NTd4AKoBCWJpbGxib2FyZNIBAA=="}, {"type": "hot_list_feed", "style_type": "1", "id": "31_1618200697.2254467", "card_id": "Q_452756142", "feed_specific": {"answer_count": 24}, "target": {"title_area": {"text": "能分析一下《创造营 2021》力丸的性格吗？"}, "excerpt_area": {"text": "我感觉他好像镜头面前好紧张？而且站位也很喜欢站旁边或者后面，每天笑呵呵的，而且感觉反应慢慢的那种。玩游戏的时候一直都很淡淡的笑，没有特别大的心情欺负那种（虽然也有笑的很开心的时候）。不过原团那些视频感觉还蛮自然的。我很想描述他的性格但是我描述不出来，想让厉害的人分析分析。"}, "image_area": {"url": "https://pic2.zhimg.com/80/v2-578a168877f273ff964cca10b00faf46_720w.png"}, "metrics_area": {"text": "122 万热度"}, "label_area": {"type": "trend", "trend": 0, "night_color": "#B7302D", "normal_color": "#F1403C"}, "link": {"url": "https://www.zhihu.com/question/452756142"}}, "attached_info": "Cj4IyOOBkpH0yqFSEAMaCDYyODkyMDA1IOfRoYMGMAM4V0Afcgk0NTI3NTYxNDJ4AKoBCWJpbGxib2FyZNIBAA=="}, {"type": "hot_list_feed", "style_type": "1", "id": "32_1618200697.2258525", "card_id": "Q_59835732", "feed_specific": {"answer_count": 228}, "target": {"title_area": {"text": "你收到的最实用的恋爱经验是什么？"}, "excerpt_area": {"text": ""}, "image_area": {"url": "https://pic3.zhimg.com/50/v2-9025263c22c7c7038e22e81326ed2891_b.jpg"}, "metrics_area": {"text": "117 万热度"}, "label_area": {"type": "trend", "trend": 0, "night_color": "#B7302D", "normal_color": "#F1403C"}, "link": {"url": "https://www.zhihu.com/question/59835732"}}, "attached_info": "Cj4IyOOBkpH0yqFSEAMaCDE2MTU3MzQ0IPiP4cgFMAY4hRRAIHIINTk4MzU3MzJ4AKoBCWJpbGxib2FyZNIBAA=="}, {"type": "hot_list_feed", "style_type": "1", "id": "33_1618200697.2261379", "card_id": "Q_342445699", "feed_specific": {"answer_count": 290}, "target": {"title_area": {"text": "你有哪些住宿必备好吃不贵的零食？"}, "excerpt_area": {"text": ""}, "image_area": {"url": "https://picb.zhimg.com/50/v2-fd886a812d10d0b6157e2302059a545d_b.jpg"}, "metrics_area": {"text": "114 万热度"}, "label_area": {"type": "trend", "trend": 0, "night_color": "#B7302D", "normal_color": "#F1403C"}, "link": {"url": "https://www.zhihu.com/question/342445699"}}, "attached_info": "Cj8IyOOBkpH0yqFSEAMaCDM4Mzc2MTg3IMzZgusFMAQ42hVAIXIJMzQyNDQ1Njk5eACqAQliaWxsYm9hcmTSAQA="}, {"type": "hot_list_feed", "style_type": "1", "id": "34_1618200697.2264056", "card_id": "Q_444986537", "feed_specific": {"answer_count": 31}, "target": {"title_area": {"text": "「足坛」有哪些公认的水货，后来莫名其妙竟然踢出来了的球员？"}, "excerpt_area": {"text": ""}, "image_area": {"url": "https://pic1.zhimg.com/80/v2-148ca2ed2d3ecb52b12039826bdca8fd_720w.jpg?source=1940ef5c"}, "metrics_area": {"text": "108 万热度"}, "label_area": {"type": "trend", "trend": 0, "night_color": "#B7302D", "normal_color": "#F1403C"}, "link": {"url": "https://www.zhihu.com/question/444986537"}}, "attached_info": "Cj4IyOOBkpH0yqFSEAMaCDYxMTY0NTk0IIigt4EGMAA4P0Aicgk0NDQ5ODY1Mzd4AKoBCWJpbGxib2FyZNIBAA=="}, {"type": "hot_list_feed", "style_type": "1", "id": "35_1618200697.226731", "card_id": "Q_22164041", "feed_specific": {"answer_count": 3569}, "target": {"title_area": {"text": "排名在前 1% 的高中生是靠天赋还是靠努力？"}, "excerpt_area": {"text": ""}, "image_area": {"url": "https://pic3.zhimg.com/80/2ccd835214280dc5b5fa1352362e5cb2_hd.jpg"}, "metrics_area": {"text": "103 万热度"}, "label_area": {"type": "trend", "trend": 0, "night_color": "#B7302D", "normal_color": "#F1403C"}, "link": {"url": "https://www.zhihu.com/question/22164041"}}, "attached_info": "Cj8IyOOBkpH0yqFSEAMaBzEwNDY1MDcg2qztlAUw4gE4tJ0DQCNyCDIyMTY0MDQxeACqAQliaWxsYm9hcmTSAQA="}, {"type": "hot_list_feed", "style_type": "1", "id": "36_1618200697.2271116", "card_id": "Q_350710025", "feed_specific": {"answer_count": 740}, "target": {"title_area": {"text": "短发可以软妹吗？"}, "excerpt_area": {"text": "日系短发"}, "image_area": {"url": "https://pic3.zhimg.com/80/v2-82760e127752f63b9ecd549a20557f56_hd.png"}, "metrics_area": {"text": "101 万热度"}, "label_area": {"type": "trend", "trend": 0, "night_color": "#B7302D", "normal_color": "#F1403C"}, "link": {"url": "https://www.zhihu.com/question/350710025"}}, "attached_info": "Cj8IyOOBkpH0yqFSEAMaCDQwMjEzNzMxILC9ke0FMCg4pS5AJHIJMzUwNzEwMDI1eACqAQliaWxsYm9hcmTSAQA="}, {"type": "hot_list_feed", "style_type": "1", "id": "37_1618200697.2277877", "card_id": "Q_453850034", "feed_specific": {"answer_count": 51}, "target": {"title_area": {"text": "4 月 10 日发布的《创造营 2021》排名，利路修卡 12，你怎么看？"}, "excerpt_area": {"text": "鹅把预告排名发出来了，利路修卡 12 了哈哈哈哈哈在出道边缘了！笋丝厉害！他会不会真的出道啊？我期待他出道的…"}, "image_area": {"url": "https://pic2.zhimg.com/50/v2-5f7868271bc064bc09b83aec16d2d6bf_b.jpg"}, "metrics_area": {"text": "95 万热度"}, "label_area": {"type": "trend", "trend": 0, "night_color": "#B7302D", "normal_color": "#F1403C"}, "link": {"url": "https://www.zhihu.com/question/453850034"}}, "attached_info": "Cj4IyOOBkpH0yqFSEAMaCDYzMTM1MTc1INS6xIMGMAA4WkAlcgk0NTM4NTAwMzR4AKoBCWJpbGxib2FyZNIBAA=="}, {"type": "hot_list_feed", "style_type": "1", "id": "38_1618200697.2282574", "card_id": "Q_453597876", "feed_specific": {"answer_count": 22}, "target": {"title_area": {"text": "贾母给了薛宝琴一件斗蓬，为什么不给林黛玉呢？"}, "excerpt_area": {"text": ""}, "image_area": {"url": "https://pic4.zhimg.com/80/v2-75ed8b4882d041a3ae8050f30a986818_720w.jpg?source=1940ef5c"}, "metrics_area": {"text": "79 万热度"}, "label_area": {"type": "trend", "trend": 0, "night_color": "#B7302D", "normal_color": "#F1403C"}, "link": {"url": "https://www.zhihu.com/question/453597876"}}, "attached_info": "Cj4IyOOBkpH0yqFSEAMaCDYzMDc5MTIyIP7qu4MGMAA4KUAmcgk0NTM1OTc4NzZ4AKoBCWJpbGxib2FyZNIBAA=="}, {"type": "hot_list_feed", "style_type": "1", "id": "39_1618200697.2286332", "card_id": "Q_454167062", "feed_specific": {"answer_count": 25}, "target": {"title_area": {"text": "如何看待多品牌共享充电宝集体涨价，景区共享充电宝 1 小时 10 元？共享电宝又涨价你还会买单吗？"}, "excerpt_area": {"text": "近日，不少消费者发现，在上海的普通商场内，不同品牌的共享充电宝在悄悄涨价。从最初的每小时 1 元，半小时免费的价格，到现在平均每小时需花费 3-4 元，而 24 小时封顶价也从 20 元涨至 30 元。 在杭州西湖景区有游客发现街电、怪兽充电、小电等充电包收费高达每小时 10 元。不仅是共享充电宝，共享单车同样在涨价。 近日，有网友提供的青桔单车计价规则截图显示，青桔单车前 15 分钟收费 1.5 元，然后每 10 分钟收费 1 元，这样算下来，1 小时收费高达 6.5 元，比乘坐公交车的价格还要贵。 此前，共享充电宝悄悄涨价了，每小时租借费用多为 3 元和 4 元，24 小时封顶价格从 20 元到 40 元不等。一部手机，电量充其量是 4000 毫安时，电费超不过 2 分钱，而一个充电宝也就几十元。两分钱的成本赚 4 元，一本百利了。"}, "image_area": {"url": "https://pic1.zhimg.com/80/v2-92c0961755b203f69c440459f005f13a_720w.jpg?source=1940ef5c"}, "metrics_area": {"text": "77 万热度"}, "label_area": {"type": "trend", "trend": 0, "night_color": "#B7302D", "normal_color": "#F1403C"}, "link": {"url": "https://www.zhihu.com/question/454167062"}}, "attached_info": "ClQIyOOBkpH0yqFSEAMaCDYzMjA1NjM3IOevzoMGMAE4IEAncgk0NTQxNjcwNjJ4AKoBCWJpbGxib2FyZNIBAPIBEwgBEg9kb21haW5fb3BlcmF0b3I="}, {"type": "hot_list_feed", "style_type": "1", "id": "40_1618200697.2293122", "card_id": "Q_453593261", "feed_specific": {"answer_count": 88}, "target": {"title_area": {"text": "你的手机里有什么舍不得删的《王者荣耀》游戏截图？"}, "excerpt_area": {"text": "可能是练了好久的英雄第一次带飞，可能是打出了历史最低评分，可能是和路人队友的搞笑对话，也可能是和朋友一起打游戏留下的珍贵回忆…"}, "image_area": {"url": "https://pic4.zhimg.com/50/v2-70e06c457373ba6c6a3de2a5b54d0e3e_b.jpg"}, "metrics_area": {"text": "75 万热度"}, "label_area": {"type": "trend", "trend": 0, "night_color": "#B7302D", "normal_color": "#F1403C"}, "link": {"url": "https://www.zhihu.com/question/453593261"}}, "attached_info": "Cj4IyOOBkpH0yqFSEAMaCDYzMDc4MTA1INbdu4MGMAI4bUAocgk0NTM1OTMyNjF4AKoBCWJpbGxib2FyZNIBAA=="}, {"type": "hot_list_feed", "style_type": "1", "id": "41_1618200697.2296731", "card_id": "Q_453992325", "feed_specific": {"answer_count": 179}, "target": {"title_area": {"text": "《英雄联盟》聊天时为什么有人喜欢发 「1」？发的 「1」 都有哪些意思？"}, "excerpt_area": {"text": "我发现打游戏经常碰见队友发 1 ，组队时也有人好打 「1」，有一次最气的时我回城不小心被对面偷袭了对面公屏给我发了个 1，而且也不知道这 1 啥意思，有老哥总结下都啥时候发 1，这发的 1 都有啥含义吗"}, "image_area": {"url": "https://pic1.zhimg.com/80/v2-790beafe99d851c9faa550f2b1028242_720w.png"}, "metrics_area": {"text": "59 万热度"}, "label_area": {"type": "trend", "trend": 0, "night_color": "#B7302D", "normal_color": "#F1403C"}, "link": {"url": "https://www.zhihu.com/question/453992325"}}, "attached_info": "Cj8IyOOBkpH0yqFSEAMaCDYzMTY2Njc3INXsyIMGMAg44QJAKXIJNDUzOTkyMzI1eACqAQliaWxsYm9hcmTSAQA="}, {"type": "hot_list_feed", "style_type": "1", "id": "42_1618200697.2302053", "card_id": "Q_453119283", "feed_specific": {"answer_count": 72}, "target": {"title_area": {"text": "大爆炸起始于一个奇点，奇点势能被打破，导致能量不断转化为物质演变为宇宙。是什么导致了奇点平衡被打破？"}, "excerpt_area": {"text": ""}, "image_area": {"url": "https://pic1.zhimg.com/v2-f2eda8629283a1cbf1d466fe856b19de_1440w.jpg?source=172ae18b"}, "metrics_area": {"text": "58 万热度"}, "label_area": {"type": "trend", "trend": 0, "night_color": "#B7302D", "normal_color": "#F1403C"}, "link": {"url": "https://www.zhihu.com/question/453119283"}}, "attached_info": "Cj8IyOOBkpH0yqFSEAMaCDYyOTcyODA3IJ2prYMGMAU43QJAKnIJNDUzMTE5MjgzeACqAQliaWxsYm9hcmTSAQA="}, {"type": "hot_list_feed", "style_type": "1", "id": "43_1618200697.2306283", "card_id": "Q_454031031", "feed_specific": {"answer_count": 100}, "target": {"title_area": {"text": "开会时，领导突然点名让你讲几句，但你却没有提前做好准备的时候，该怎么办？"}, "excerpt_area": {"text": "开会的时候，各个部门的人都在，领导突然点名让你讲几句，但你没有事先准备过，而且又要面对这么多其他部门的人和负责人，你该怎么应对？"}, "image_area": {"url": "https://pic4.zhimg.com/80/v2-633a39d92d9e1068177c3c9f287b3657_720w.jpg?source=1940ef5c"}, "metrics_area": {"text": "58 万热度"}, "label_area": {"type": "trend", "trend": 0, "night_color": "#B7302D", "normal_color": "#F1403C"}, "link": {"url": "https://www.zhihu.com/question/454031031"}}, "attached_info": "Cj8IyOOBkpH0yqFSEAMaCDYzMTc1MzUzIM6AyoMGMAY4xA5AK3IJNDU0MDMxMDMxeACqAQliaWxsYm9hcmTSAQA="}, {"type": "hot_list_feed", "style_type": "1", "id": "44_1618200697.231145", "card_id": "Q_438455489", "feed_specific": {"answer_count": 164}, "target": {"title_area": {"text": "有没有高级感的思念文案?"}, "excerpt_area": {"text": "请广大网友开始表演才艺的时候到了，"}, "image_area": {"url": "https://pic1.zhimg.com/80/v2-7116f32b0259c58257f8677b993880cd_720w.jpg?source=1940ef5c"}, "metrics_area": {"text": "57 万热度"}, "label_area": {"type": "trend", "trend": 0, "night_color": "#B7302D", "normal_color": "#F1403C"}, "link": {"url": "https://www.zhihu.com/question/438455489"}}, "attached_info": "Cj8IyOOBkpH0yqFSEAMaCDU5NzEyODY0IKWn4P8FMAE4wQxALHIJNDM4NDU1NDg5eACqAQliaWxsYm9hcmTSAQA="}, {"type": "hot_list_feed", "style_type": "1", "id": "45_1618200697.2315576", "card_id": "Q_38031736", "feed_specific": {"answer_count": 94}, "target": {"title_area": {"text": "有什么好看的适合 20 岁女生佩戴的项链？"}, "excerpt_area": {"text": "如题，在校大学生，希望大家推荐一些好看的项链，银的铂金的彩金的镶钻的都可以，推荐些比较好的牌子或者款式，价格 1000 到 3000 之间，谢谢大家啦！"}, "image_area": {"url": "https://pic1.zhimg.com/50/v2-7da5318f7e322779961f75cc9ccec1bb_b.jpg"}, "metrics_area": {"text": "56 万热度"}, "label_area": {"type": "trend", "trend": 0, "night_color": "#B7302D", "normal_color": "#F1403C"}, "link": {"url": "https://www.zhihu.com/question/38031736"}}, "attached_info": "Cj0IyOOBkpH0yqFSEAMaBzc0MTk5NDEgkObvsgUwADivBUAtcggzODAzMTczNngAqgEJYmlsbGJvYXJk0gEA"}, {"type": "hot_list_feed", "style_type": "1", "id": "46_1618200697.2319684", "card_id": "Q_355087220", "feed_specific": {"answer_count": 70}, "target": {"title_area": {"text": "对于久坐的人，屁股下加个坐垫有用吗？"}, "excerpt_area": {"text": "10 小时以上"}, "image_area": {"url": "https://pic4.zhimg.com/80/v2-bb627692e6c562d3209c1e5315fe0689_720w.jpg?source=1940ef5c"}, "metrics_area": {"text": "53 万热度"}, "label_area": {"type": "trend", "trend": 0, "night_color": "#B7302D", "normal_color": "#F1403C"}, "link": {"url": "https://www.zhihu.com/question/355087220"}}, "attached_info": "Cj8IyOOBkpH0yqFSEAMaCDQxMTg2MTMxIPOLne4FMAU46AVALnIJMzU1MDg3MjIweACqAQliaWxsYm9hcmTSAQA="}, {"type": "hot_list_feed", "style_type": "1", "id": "47_1618200697.2324033", "card_id": "Q_452942849", "feed_specific": {"answer_count": 283}, "target": {"title_area": {"text": "安徽农业大学学生拒服兵役被罚 4 万余元，两年内不得复学，什么算拒服兵役？后果有多严重？"}, "excerpt_area": {"text": "刘帅，男，汉族，河北省邯郸市临漳县人，该同志 2019 年考入安徽农业大学，2020 年 9 月经体格检查、政治考核、役前训练、审批定兵等手续正常入伍，被分配至新疆军区某部服役。2020 年 9 月 17 日到达部队后，次日该同志就表现出不适应，提出要离开部队。经部队及其家人多次思想教育和引导无效后，中共南疆军区纪律检查委员会于 2020 年 11 月 6 日对刘帅做出拒服兵役除名处理决定。 按照相关规定，安徽农业大学于 2020 年 12 月 21 日给予刘帅两年内不得复学的处理意见。 依据《中华人民共和国兵役法》《征兵工作条例》等法律规定，综合学校处理意见，经蜀山区征兵领导小组会议研究通过，区征兵办决定对安徽农业大学拒服兵役应征大学生刘帅作如下处罚： 1. 取消其义务兵优待，按蜀山区当年义务兵家庭优待金的 2 倍 46866 元予以罚款（2020 年蜀山区义务兵家庭优待金标准为 23433 元）， 由琥珀街道办事处联合安徽农业大学执行，罚款上缴区财政（欠款汇入账号由区财政局提供）。逾期拒不缴纳罚款，申请人民法院强制执行。 2. 将其纳入履行国防义务严重失信主体名单实施联合惩戒，金融部门 3 年内不得给予其信贷优惠政策和利率优惠政策。 3. 蜀山区组织、人社等部门不得录用其为公务员或者参照公务员法管理的工作人员、事业单位人员及国有企业工作人员。 4. 安徽农业大学 2 年内不得为其办理复学手续。 5. 蜀山区媒体单位将其作为违反《兵役法》的反面典型，向社会通报。 6. 函告户籍地兵役机关，请户籍地公安部门在其个人户籍「兵役栏」备注「拒服兵役」永久字样，2 年内不得为其办理出国（境）手续。 7. 函告户籍地兵役机关，请户籍地民政、住建部门不得将其纳入困难补助及保障性安居工程保障范围。 8. 函告户籍地兵役机关，请户籍地行政审批部门 3 年内不得为其办理经商办企业手续。 此决定自发文之日起逐步落实，2021 年 6 月底前完成 关于 2020 年拒服兵役新兵刘帅的处理决定"}, "image_area": {"url": "https://pic1.zhimg.com/80/v2-9a91884dad0d3e11ec8fe66644a366a0_1440w.jpg?source=1940ef5c"}, "metrics_area": {"text": "51 万热度"}, "label_area": {"type": "trend", "trend": 0, "night_color": "#B7302D", "normal_color": "#F1403C"}, "link": {"url": "https://www.zhihu.com/question/452942849"}}, "attached_info": "Cj8IyOOBkpH0yqFSEAMaCDYyOTMzNTMyIMe2p4MGMEM4wQlAL3IJNDUyOTQyODQ5eACqAQliaWxsYm9hcmTSAQA="}, {"type": "hot_list_feed", "style_type": "1", "id": "48_1618200697.23325", "card_id": "Q_375010303", "feed_specific": {"answer_count": 62}, "target": {"title_area": {"text": "你后悔选择人力资源工作吗？"}, "excerpt_area": {"text": "本人本科人力资源管理专业毕业，工作有三年多，招聘工作一直没放下，其中也接触过培训、员工关系模块，遇到气场比较合的领导，干的也还算开心，也没想太多，但是最近越来越觉得人力资源工作的天花板很低，每天加班加点，招聘压力大，money 吧，也没挣多少，关键还觉得学不到什么东西，对我未来的成长帮助不大，不能帮我走上人生巅峰，感觉这样下去会碌碌无为一辈子，大家可以给我些建议吗？"}, "image_area": {"url": "https://pic2.zhimg.com/80/v2-55d5d586064836cfe95fe3393deae1e6_qhd.jpg"}, "metrics_area": {"text": "50 万热度"}, "label_area": {"type": "trend", "trend": 0, "night_color": "#B7302D", "normal_color": "#F1403C"}, "link": {"url": "https://www.zhihu.com/question/375010303"}}, "attached_info": "Cj8IyOOBkpH0yqFSEAMaCDQ1NjE0MTM4IMvq3PIFMAA49wVAMHIJMzc1MDEwMzAzeACqAQliaWxsYm9hcmTSAQA="}, {"type": "hot_list_feed", "style_type": "1", "id": "49_1618200697.23374", "card_id": "Q_423321345", "feed_specific": {"answer_count": 497}, "target": {"title_area": {"text": "中国特有的狸花猫有多强大？"}, "excerpt_area": {"text": ""}, "image_area": {"url": "https://pic2.zhimg.com/80/v2-8bcf6ad73f2a3e33dee1470c60101e3a_720w.jpg?source=1940ef5c"}, "metrics_area": {"text": "50 万热度"}, "label_area": {"type": "trend", "trend": 0, "night_color": "#B7302D", "normal_color": "#F1403C"}, "link": {"url": "https://www.zhihu.com/question/423321345"}}, "attached_info": "Cj8IyOOBkpH0yqFSEAMaCDU2MzUwMDk3INrDxvsFMBE4qBZAMXIJNDIzMzIxMzQ1eACqAQliaWxsYm9hcmTSAQA="}], "paging": {"is_end": true, "next": "", "previous": ""}, "fresh_text": "热榜已更新"}